codice/__init__.py
codice/cfsearch.py
codice/config.py
codice/dataset.py
codice/dataset_metadata.py
codice/explainer.py
codice/feature_manager.py
codice/load_datasets.py
codice/optim_config.py
codice/setup.py
codice/train.py
codice/transformer.py
codice/cefeature/__init__.py
codice/cefeature/feature_sampler.py
codice/ceinstance/__init__.py
codice/ceinstance/instance_factory.py
codice/ceinstance/instance_sampler.py
codice-0.2.9.data/data/LICENSE
codice-0.2.9.data/data/README.md
tests/__init__.py
tests/test_breast_cancer.py
tests/test_compas.py
tests/test_counterfactual_regression.py
tests/test_counterfactual_search.py
tests/test_counterfactual_spiral.py
tests/test_dataset_read.py
tests/test_diabetes_ablation.py
tests/test_diabetes_coherence.py
tests/test_diffusion.py
tests/test_entire_pipeline_gp.py
tests/test_evaluation_adult.py
tests/test_evaluation_breast_cancer.py
tests/test_evaluation_compas.py
tests/test_evaluation_diabetes.py
tests/test_evaluation_diabetes_ablation.py
tests/test_evaluation_energy.py
tests/test_evaluation_german.py
tests/test_evaluation_homeloan.py
tests/test_german.py
tests/test_gp_expression.py
tests/test_homeloan_coherence.py
tests/test_instance_creation.py
tests/test_normalization.py
tests/test_reading_model.py
tests/test_swiss_roll.py
tests/test_train_model.py
tests/test_transformer.py
trustce/__init__.py
trustce/cfsearch.py
trustce/config.py
trustce/dataset.py
trustce/dataset_metadata.py
trustce/explainable_model.py
trustce/explainer.py
trustce/feature_manager.py
trustce/load_datasets.py
trustce/optim_config.py
trustce/setup.py
trustce/train.py
trustce/transformer.py
trustce/cefeature/__init__.py
trustce/cefeature/feature_sampler.py
trustce/ceinstance/__init__.py
trustce/ceinstance/instance_factory.py
trustce/ceinstance/instance_sampler.py
codice-0.2.9.dist-info/LICENSE
codice-0.2.9.dist-info/METADATA
codice-0.2.9.dist-info/WHEEL
codice-0.2.9.dist-info/top_level.txt
codice-0.2.9.dist-info/RECORD
