Metadata-Version: 2.1
Name: codice
Version: 0.2.9
License-File: LICENSE
Requires-Dist: numpy ==1.26.1
Requires-Dist: pandas ==1.5.3
Requires-Dist: scikit-learn ==1.3.1
Requires-Dist: scipy ==1.11.3
Requires-Dist: pydiffmap ==0.2.0.1
Requires-Dist: Pillow ==10.0.1
Requires-Dist: PyYAML ==6.0.1
Requires-Dist: requests ==2.31.0
Requires-Dist: ipykernel >=5.5.6
Provides-Extra: dev
Requires-Dist: pytest >=7.4.4 ; extra == 'dev'
Provides-Extra: diabetes
Provides-Extra: gpgomea
Requires-Dist: gpgomea >=0.1.0 ; extra == 'gpgomea'
Provides-Extra: homeloan
Provides-Extra: income
Provides-Extra: pytorch
Requires-Dist: torch >=1.8.1 ; extra == 'pytorch'
Provides-Extra: sklearn
Requires-Dist: scikit-learn >=0.24.1 ; extra == 'sklearn'
Provides-Extra: tensorflow
Requires-Dist: tensorflow >=2.14.1 ; extra == 'tensorflow'
